LICENSE.txt
MANIFEST.in
README.md
requirements.txt
setup.cfg
setup.py
sklearn_gbmi/__init__.py
sklearn_gbmi/_partial_dependence_tree.c
sklearn_gbmi/_partial_dependence_tree.pyx
sklearn_gbmi/partial_dependence.py
sklearn_gbmi/sklearn_gbmi.py
sklearn_gbmi.egg-info/PKG-INFO
sklearn_gbmi.egg-info/SOURCES.txt
sklearn_gbmi.egg-info/dependency_links.txt
sklearn_gbmi.egg-info/requires.txt
sklearn_gbmi.egg-info/top_level.txt
sklearn_gbmi.egg-info/zip-safe