Metadata-Version: 1.1
Name: sklearn-gbmi
Version: 1.0.3
Summary: Compute Friedman and Popescu's H statistics, in order to look for interactions among variables in scikit-learn gradient-boosting models.
Home-page: https://github.com/ralphhaygood/sklearn-gbmi
Author: Ralph Haygood
Author-email: ralph@ralphhaygood.org
License: MIT
Download-URL: https://github.com/ralphhaygood/sklearn-gbmi/tarball/1.0.3
Keywords: boosted,boosting,data science,Friedman,gradient boosted,gradient boosting,H statistic,interaction,machine learning,Popescu,scikit learn,sklearn
Platform: UNKNOWN
Classifier: Development Status :: 5 - Production/Stable
Classifier: Intended Audience :: Science/Research
Classifier: License :: OSI Approved :: MIT License
Classifier: Natural Language :: English
Classifier: Programming Language :: Python :: 2
Classifier: Programming Language :: Python :: 2.7
Classifier: Programming Language :: Python :: 3
Classifier: Programming Language :: Python :: 3.5
Classifier: Topic :: Scientific/Engineering
